{
  "stream": "stream-e-assistant",
  "agent": "Assistant",
  "status": "not_started",
  "started_at": null,
  "last_updated": "2024-12-05T23:00:00Z",
  "progress": "0%",
  "current_task": "Waiting to start",
  "completed_tasks": [],
  "next_tasks": [
    "Read assigned.md",
    "Review requirements document",
    "Review agent-interfaces.md",
    "Read STYLE_GUIDE.MD",
    "Refine Differentiator prompt",
    "Implement Differentiator agent",
    "Refine Tailoring Agent prompt",
    "Implement Tailoring Agent",
    "Write tests"
  ],
  "blockers": [
    "Depends on Stream D (Interrogator-Prepper) completing first"
  ],
  "notes": "Ready to start once Interrogator-Prepper is available. See assigned.md for details."
}
